Metadata-Version: 2.4
Name: mcpath
Version: 2.1.0
Summary: Get paths to Minecraft Java, Bedrock, Preview, and Education Edition folders.
Home-page: https://github.com/legopitstop/mcpath/
Author: Legopitstop
Author-email: contact@lpsmods.dev
License: MIT
Project-URL: Download, https://github.com/legopitstop/mcpath/releases
Project-URL: Documentation, https://docs.lpsmods.dev/mcpath/
Project-URL: Source Code, https://github.com/legopitstop/mcpath
Keywords: minecraft,paths,java,bedrock,preview,education,world,screenshots,resourcepacks,behaviorpacks
Classifier: Development Status :: 5 - Production/Stable
Classifier: Intended Audience :: Developers
Classifier: License :: OSI Approved :: MIT License
Classifier: Programming Language :: Python :: 3.10
Classifier: Programming Language :: Python :: 3.11
Classifier: Programming Language :: Python :: 3.12
Classifier: Programming Language :: Python :: 3.13
Classifier: Programming Language :: Python :: 3.14
Requires-Python: >=3.10
License-File: LICENSE
Requires-Dist: requests
Requires-Dist: requests-cache
Requires-Dist: typing_extensions
Provides-Extra: testing
Requires-Dist: pytest>=6.0; extra == "testing"
Requires-Dist: pytest-cov>=2.0; extra == "testing"
Requires-Dist: mypy>=1.11.2; extra == "testing"
Requires-Dist: flake8>=3.9; extra == "testing"
Requires-Dist: tox>=3.24; extra == "testing"
Dynamic: license-file
